deepwhy/__init__.py
deepwhy-0.1.0.dist-info/METADATA
deepwhy-0.1.0.dist-info/WHEEL
deepwhy-0.1.0.dist-info/RECORD
