Metadata-Version: 2.1
Name: deepwhy
Version: 0.1.0
Summary: Deep Learning for Causal Inference
Author: Yajie Zhu
Author-email: yajiez.me@gmail.com
Requires-Python: >=3.11,<3.12
Classifier: Programming Language :: Python :: 3
Classifier: Programming Language :: Python :: 3.11
Requires-Dist: causal-learn (>=0.1.3.8,<0.2.0.0)
Requires-Dist: dowhy (>=0.11.1,<0.12.0)
Requires-Dist: econml (>=0.15.1,<0.16.0)
Requires-Dist: pandas (>=2.2.3,<3.0.0)
Requires-Dist: scikit-learn (>=1.5.2,<2.0.0)
Requires-Dist: seaborn (>=0.13.2,<0.14.0)
Requires-Dist: torch (>=2.5.1,<3.0.0)
